{
  "rootId": "tile-layout-1000076487588835",
  "elements": {
    "tile-layout-1000076487588835": {
      "Name": "TileLayout",
      "props": {
        "columns": 6,
        "noGutter": false,
        "children": {
          "uxpinPresetElementId": "tile-layout-item-1000052882014382",
          "uxpinPresetElementId": "tile-layout-item-1000052882014383",
          "uxpinPresetElementId": "tile-layout-item-1000052882014384"
        }
      }
    },
    "tile-layout-item-1000052882014382": {
      "name": "TileLayoutItem",
      "props": {
        "style": {
          "width": "200px",
          "height": "200px",
          "backgroundColor": "#444"
        },
        "children": "Hello 1"
      }
    },
    "tile-layout-item-1000052882014383": {
      "name": "TileLayoutItem",
      "props": {
        "style": {
          "width": "200px",
          "height": "200px",
          "backgroundColor": "#444"
        },
        "children": "Hello 1"
      }
    },
    "tile-layout-item-1000052882014384": {
      "name": "TileLayoutItem",
      "props": {
        "style": {
          "width": "200px",
          "height": "200px",
          "backgroundColor": "#444"
        },
        "children": "Hello 1"
      }
    }
  }
}
